README.md
setup.cfg
setup.py
Arbd/__init__.py
arbdlib.egg-info/PKG-INFO
arbdlib.egg-info/SOURCES.txt
arbdlib.egg-info/dependency_links.txt
arbdlib.egg-info/requires.txt
arbdlib.egg-info/top_level.txt