Metadata-Version: 1.0
Name: arbdlib
Version: 1.0
Summary: package to control sensors and actuators present on ARBD1
Home-page: https://github.com/hatchnhack/arbd1-lib
Author: Shashikant Chaudhary
Author-email: contact@hatchnhack.com
License: GPL-3.0
Platform: UNKNOWN
